asv_bwrap/__init__.py
asv_bwrap/__main__.py
asv_bwrap/_version.py
asv_bwrap/main.py
asv_bwrap/scripts/preamble1.sh
asv_bwrap/scripts/run1.sh
asv_bwrap-0.1.dist-info/entry_points.txt
asv_bwrap-0.1.dist-info/LICENSE.rst
asv_bwrap-0.1.dist-info/WHEEL
asv_bwrap-0.1.dist-info/METADATA
asv_bwrap-0.1.dist-info/RECORD
