Metadata-Version: 2.1
Name: asv-bwrap
Version: 0.1
Summary: Manage running Airspeed Velocity (asv) benchmarks in a lightweight
Home-page: https://github.com/pv/asv-bwrap
License: UNKNOWN
Author: Pauli Virtanen
Author-email: pav@iki.fi
Requires-Python: >=3.5
Classifier: Topic :: Software Development :: Testing
Classifier: Intended Audience :: Developers
Classifier: Environment :: Console
Classifier: License :: OSI Approved :: BSD License
Classifier: Programming Language :: Python :: 3
Requires-Dist: lockfile
Requires-Dist: qtoml; python_version>='3.6'
Requires-Dist: toml; python_version<'3.6'
Requires-Dist: pytest>=4.0.0; extra == "test"
Provides-Extra: test
